ds3/__init__.py
ds3-0.1.0.dist-info/WHEEL
ds3-0.1.0.dist-info/METADATA
ds3-0.1.0.dist-info/RECORD
