Metadata-Version: 2.1
Name: ds3
Version: 0.1.0
Summary: The S3 API for Python
Author: Tomas Pereira de Vasconcelos
Author-email: tomasvasconcelos1@gmail.com
Requires-Python: >=3.7,<4.0
Classifier: Programming Language :: Python :: 3
Classifier: Programming Language :: Python :: 3.7
Classifier: Programming Language :: Python :: 3.8
